Metadata-Version: 2.1
Name: statusDadosjusbr
Version: 0.3
Summary: Contém os status de execução dos coletores do DadosjusBr
Home-page: https://github.com/dadosjusbr/status/
Author: Dadosjusbr
Author-email: dadosjusbr@gmail.com
License: UNKNOWN
Platform: UNKNOWN
Classifier: Programming Language :: Python :: 3
Classifier: License :: OSI Approved :: MIT License
Classifier: Operating System :: OS Independent
